py4linear_regression/__init__.py
py4linear_regression/regression.py
py4linear_regression-0.0.5.dist-info/METADATA
py4linear_regression-0.0.5.dist-info/WHEEL
py4linear_regression-0.0.5.dist-info/top_level.txt
py4linear_regression-0.0.5.dist-info/RECORD
